logistic_module/__init__.py
logistic_module/LogisticEquation/Bifurcation.py
logistic_module/LogisticEquation/Logistic_and_vectorization.py
logistic_module/LogisticEquation/Visualization.py
logistic_module/LogisticEquation/__init__.py
logistic_module/LogisticEquation/script.py
logistic_module/Mandelbrot2D/Inside_Mandelbrotset.py
logistic_module/Mandelbrot2D/Mandelbrot2D.py
logistic_module/Mandelbrot2D/Mandelbrot2DAnimation.py
logistic_module/Mandelbrot2D/Plot_pattern.py
logistic_module/Mandelbrot2D/__init__.py
logistic_module/Mandelbrot2D/script.py
logistic_module/Mandelbrot3D/Mandelbrot3D.py
logistic_module/Mandelbrot3D/Mandelbrot3D_anim.py
logistic_module/Mandelbrot3D/__init__.py
logistic_module/Mandelbrot3D/script.py
logistic_module-2.0.1.dist-info/METADATA
logistic_module-2.0.1.dist-info/WHEEL
logistic_module-2.0.1.dist-info/top_level.txt
logistic_module-2.0.1.dist-info/RECORD
