Metadata-Version: 2.1
Name: logistic-module
Version: 2.0.1
Summary: Visualization of Mandelbrot fractal in 3D
Home-page: https://github.com/hannabacave/Logistic_module
Author: Cindy Delage, Hanna Bacave, Yassine Mimouni
Author-email: UNKNOWN
License: UNKNOWN
Platform: UNKNOWN
Requires-Dist: matplotlib (==3.1.2)
Requires-Dist: numpy (==1.18.1)
Requires-Dist: numba (==0.47.0)
Requires-Dist: plotly (==4.6.0)
Requires-Dist: scipy (==1.3.1)
Requires-Dist: memory-profiler
